odoo/addons/shopinvader_base_url/README.rst
odoo/addons/shopinvader_base_url/__init__.py
odoo/addons/shopinvader_base_url/__manifest__.py
odoo/addons/shopinvader_base_url/i18n/base_url.pot
odoo/addons/shopinvader_base_url/i18n/shopinvader_base_url.pot
odoo/addons/shopinvader_base_url/models/__init__.py
odoo/addons/shopinvader_base_url/models/abstract_url.py
odoo/addons/shopinvader_base_url/models/url_url.py
odoo/addons/shopinvader_base_url/security/ir.model.access.csv
odoo/addons/shopinvader_base_url/security/res_groups.xml
odoo/addons/shopinvader_base_url/tests/__init__.py
odoo/addons/shopinvader_base_url/tests/models.py
odoo/addons/shopinvader_base_url/tests/test_abstract_url.py
odoo/addons/shopinvader_base_url/views/url_view.xml
odoo_addon_shopinvader_base_url-16.0.1.0.3.dist-info/METADATA
odoo_addon_shopinvader_base_url-16.0.1.0.3.dist-info/WHEEL
odoo_addon_shopinvader_base_url-16.0.1.0.3.dist-info/top_level.txt
odoo_addon_shopinvader_base_url-16.0.1.0.3.dist-info/RECORD
