Metadata-Version: 2.1
Name: odoo-addon-shopinvader-base-url
Version: 16.0.1.0.3
Summary: keep history of url for products & categories
Home-page: https://github.com/shopinvader/odoo-shopinvader
Author: Akretion, ACSONE SA/NV
License: AGPL-3
Platform: UNKNOWN
Classifier: Programming Language :: Python
Classifier: Framework :: Odoo
Classifier: Framework :: Odoo :: 16.0
Classifier: License :: OSI Approved :: GNU Affero General Public License v3
Requires-Python: >=3.10
Requires-Dist: odoo-addon-base-sparse-field-list-support <16.1dev,>=16.0dev
Requires-Dist: odoo <16.1dev,>=16.0a
Requires-Dist: python-slugify
